LOTUS_regression/__init__.py
LOTUS_regression/_version.py
LOTUS_regression/cli.py
LOTUS_regression/regression.py
LOTUS_regression/dataset/__init__.py
LOTUS_regression/dataset/sbuv.py
LOTUS_regression/plotting/__init__.py
LOTUS_regression/plotting/trends.py
LOTUS_regression/predictors/__init__.py
LOTUS_regression/predictors/seasonal.py
LOTUS_regression/predictors/data/pred_baseline_eesc.csv
LOTUS_regression/predictors/data/pred_baseline_ilt.csv
LOTUS_regression/predictors/data/pred_baseline_ilt_continuous.csv
LOTUS_regression/predictors/data/pred_baseline_ilt_linear_gap.csv
LOTUS_regression/predictors/data/pred_baseline_pwlt.csv
LOTUS_regression/predictors/data/pred_extra.csv
LOTUS_regression/predictors/data/predictors.csv
LOTUS_regression/predictors/download/__init__.py
LOTUS_regression/tests/__init__.py
LOTUS_regression/tests/test_regression.py
LOTUS_regression/tests/data/S2_OSIRIS_OMPS_alt_nd_sample.csv
LOTUS_regression/tests/data/predictors.csv
LOTUS_regression-0.8.3.dist-info/LICENSE
LOTUS_regression-0.8.3.dist-info/METADATA
LOTUS_regression-0.8.3.dist-info/WHEEL
LOTUS_regression-0.8.3.dist-info/top_level.txt
LOTUS_regression-0.8.3.dist-info/RECORD
