Metadata-Version: 2.1
Name: LOTUS-regression
Version: 0.8.3
Summary: Regression model developed for the LOTUS project
Author-email: usask-arg <daniel.zawada@usask.ca>
Classifier: Development Status :: 4 - Beta
Classifier: Programming Language :: Python :: 3 :: Only
Classifier: Programming Language :: Python :: 3.10
Classifier: Programming Language :: Python :: 3.11
Classifier: Programming Language :: Python :: 3.12
Requires-Python: >=3.10
License-File: LICENSE
Requires-Dist: numpy
Requires-Dist: scipy
Requires-Dist: pandas
Requires-Dist: xarray
Requires-Dist: statsmodels
Requires-Dist: requests
Requires-Dist: appdirs
Provides-Extra: test
Requires-Dist: pytest ; extra == 'test'
